FacebookData/Facebook.py
FacebookData/__init__.py
FacebookData/desktop.ini
GoogleAnalyticsData/GoogleAnalyticsFor3Data.py
GoogleAnalyticsData/__init__.py
GoogleAnalyticsData/desktop.ini
LinkedInData/Linkedin.py
LinkedInData/__init__.py
LinkedInData/desktop.ini
ScrapingData-0.1.dist-info/LICENSE
ScrapingData-0.1.dist-info/METADATA
ScrapingData-0.1.dist-info/WHEEL
ScrapingData-0.1.dist-info/top_level.txt
ScrapingData-0.1.dist-info/RECORD
