Metadata-Version: 2.1
Name: ScrapingData
Version: 0.1
Summary: Un package pour le scraping de données de réseaux sociaux.
Home-page: https://github.com/Mariemromdhane21/ScrapingData
Author: Mariem Romdhane
Author-email: romdhanemariem21@gmail.com
License: MIT
Platform: UNKNOWN
Classifier: Programming Language :: Python :: 3
Classifier: License :: OSI Approved :: MIT License
Classifier: Operating System :: OS Independent
Requires-Dist: requests
Requires-Dist: pytz
Requires-Dist: numpy
Requires-Dist: pandas
Requires-Dist: google-analytics-data
